bpl/__init__.py
bpl/models.py
bpl/plotting.py
bpl/stan_models.py
bpl/util.py
bpl/stan_model/with_covariates.pkl
bpl/stan_model/without_covariates.pkl
bpl/test/__init__.py
bpl/test/test_bpl.py
bpl/test/test_data.csv
bpl/test/test_feats.csv
bpl-0.1.1.dist-info/LICENSE
bpl-0.1.1.dist-info/METADATA
bpl-0.1.1.dist-info/WHEEL
bpl-0.1.1.dist-info/top_level.txt
bpl-0.1.1.dist-info/RECORD
