Metadata-Version: 2.1
Name: bpl
Version: 0.1.1
Summary: Bayesian models for football leagues
Home-page: https://github.com/anguswilliams91/bpl
Author: Angus Williams <anguswilliams91@gmail.com>
Author-email: anguswilliams91@gmail.com
License: GPL-3.0
Download-URL: https://github.com/anguswilliams91/bpl/archive/master.zip
Platform: UNKNOWN
Requires-Dist: Cython (>=0.22)
Requires-Dist: pystan (~=2.19.1.1)
Requires-Dist: numpy (>=1.10.0)
Requires-Dist: pandas (>=0.20.1)
Requires-Dist: scipy (>=1.1.0)
Requires-Dist: tqdm (>=4.25.0)
